cocatools/__init__.py
cocatools/cookiecutter_templates/__init__.py
cocatools/cookiecutter_templates/django_template/cookiecutter.json
cocatools/cookiecutter_templates/django_template/setup.py
cocatools/cookiecutter_templates/django_template/{{cookiecutter.project_name}}/.bumpversion.cfg
cocatools/cookiecutter_templates/django_template/{{cookiecutter.project_name}}/.dockerignore
cocatools/cookiecutter_templates/django_template/{{cookiecutter.project_name}}/.flake8
cocatools/cookiecutter_templates/django_template/{{cookiecutter.project_name}}/.gitignore
cocatools/cookiecutter_templates/django_template/{{cookiecutter.project_name}}/.pre-commit-config.yaml
cocatools/cookiecutter_templates/django_template/{{cookiecutter.project_name}}/.vscode/settings.json
cocatools/cookiecutter_templates/django_template/{{cookiecutter.project_name}}/Dockerfile
cocatools/cookiecutter_templates/django_template/{{cookiecutter.project_name}}/Makefile
cocatools/cookiecutter_templates/django_template/{{cookiecutter.project_name}}/README.md
cocatools/cookiecutter_templates/django_template/{{cookiecutter.project_name}}/configs/__init__.py
cocatools/cookiecutter_templates/django_template/{{cookiecutter.project_name}}/configs/gunicorn_config.py
cocatools/cookiecutter_templates/django_template/{{cookiecutter.project_name}}/configs/uvicorn.py
cocatools/cookiecutter_templates/django_template/{{cookiecutter.project_name}}/data/postgres/.gitignore
cocatools/cookiecutter_templates/django_template/{{cookiecutter.project_name}}/data/redis/.gitignore
cocatools/cookiecutter_templates/django_template/{{cookiecutter.project_name}}/docs/index.md
cocatools/cookiecutter_templates/django_template/{{cookiecutter.project_name}}/docs/tutorials.md
cocatools/cookiecutter_templates/django_template/{{cookiecutter.project_name}}/envs/.gitignore
cocatools/cookiecutter_templates/django_template/{{cookiecutter.project_name}}/envs/example.env
coca_tools-0.2.4.dist-info/METADATA
coca_tools-0.2.4.dist-info/WHEEL
coca_tools-0.2.4.dist-info/entry_points.txt
coca_tools-0.2.4.dist-info/RECORD
